firewheel/__init__.py
firewheel/cli/__init__.py
firewheel/cli/configure_firewheel.py
firewheel/cli/executable_section.py
firewheel/cli/firewheel_cli.py
firewheel/cli/helper.py
firewheel/cli/helper_group.py
firewheel/cli/host_accessor.py
firewheel/cli/init_firewheel.py
firewheel/cli/section.py
firewheel/cli/ssh_manager.py
firewheel/cli/utils.py
firewheel/cli/completion/__init__.py
firewheel/cli/completion/actions.py
firewheel/cli/completion/completion-template.sh
firewheel/cli/completion/get_available_cli_commands.py
firewheel/cli/completion/get_model_component_names.py
firewheel/cli/completion/get_total_model_components_size.py
firewheel/cli/completion/prepare_completion_script.py
firewheel/cli/executors/__init__.py
firewheel/cli/executors/abstract_executor.py
firewheel/cli/executors/helpers.py
firewheel/cli/executors/local_python.py
firewheel/cli/executors/python.py
firewheel/cli/executors/shell.py
firewheel/cli/helpers/experiment
firewheel/cli/helpers/scp
firewheel/cli/helpers/ssh
firewheel/cli/helpers/start
firewheel/cli/helpers/status
firewheel/cli/helpers/time
firewheel/cli/helpers/example_helpers/pytest
firewheel/cli/helpers/example_helpers/test
firewheel/cli/helpers/example_helpers/subgroup/index
firewheel/cli/helpers/example_helpers/subgroup/test
firewheel/cli/helpers/mc/dep_graph
firewheel/cli/helpers/mc/generate
firewheel/cli/helpers/mc/list
firewheel/cli/helpers/mm/clean_bridge
firewheel/cli/helpers/mm/clear_cache
firewheel/cli/helpers/mm/flush_locks
firewheel/cli/helpers/mm/make_bridge
firewheel/cli/helpers/mm/mesh
firewheel/cli/helpers/mm/show_caches
firewheel/cli/helpers/pull/file
firewheel/cli/helpers/push/file
firewheel/cli/helpers/repository/install
firewheel/cli/helpers/repository/list
firewheel/cli/helpers/repository/uninstall
firewheel/cli/helpers/restart/experiment
firewheel/cli/helpers/restart/hard
firewheel/cli/helpers/restart/index
firewheel/cli/helpers/stop/hard
firewheel/cli/helpers/stop/index
firewheel/cli/helpers/test/all
firewheel-2.10.0.dist-info/LICENSE
firewheel-2.10.0.dist-info/METADATA
firewheel-2.10.0.dist-info/NOTICE
firewheel-2.10.0.dist-info/WHEEL
firewheel-2.10.0.dist-info/entry_points.txt
firewheel-2.10.0.dist-info/top_level.txt
firewheel-2.10.0.dist-info/RECORD
