Metadata-Version: 2.2
Name: firewheel
Version: 2.10.0
Summary: FIREWHEEL is an experiment orchestration tool that assists a user in building, controlling, observing, and analyzing repeatable experiments of distributed network systems at any scale.
Author-email: FIREWHEEL Developers <firewheel@sandia.gov>
License: Apache-2.0
Project-URL: homepage, https://www.sandia.gov/emulytics
Project-URL: documentation, https://sandialabs.github.io/firewheel/
Project-URL: repository, https://github.com/sandialabs/firewheel/
Project-URL: issue_tracker, https://github.com/sandialabs/firewheel/issues
Project-URL: changelog, https://sandialabs.github.io/firewheel/developer/changelog.html
Keywords: FIREWHEEL,Phenix,Sandia,Emulytics,emulation,distributed systems,emulation,experimentation,minimega
Classifier: Development Status :: 5 - Production/Stable
Classifier: Environment :: Console
Classifier: Intended Audience :: Developers
Classifier: Intended Audience :: Information Technology
Classifier: Intended Audience :: Telecommunications Industry
Classifier: Intended Audience :: Science/Research
Classifier: Natural Language :: English
Classifier: Operating System :: POSIX :: Linux
Classifier: Programming Language :: Python :: 3 :: Only
Classifier: Programming Language :: Python :: 3.8
Classifier: Programming Language :: Python :: 3.9
Classifier: Programming Language :: Python :: 3.10
Classifier: Programming Language :: Python :: 3.11
Classifier: Programming Language :: Python :: 3.12
Classifier: Programming Language :: Python :: 3.13
Classifier: Topic :: Internet
Classifier: Topic :: Scientific/Engineering
Classifier: Topic :: Scientific/Engineering :: Information Analysis
Classifier: Topic :: Security
Classifier: Topic :: Software Development :: Libraries
Classifier: Topic :: Software Development :: Libraries :: Application Frameworks
Classifier: Topic :: Software Development :: Testing
Classifier: Topic :: System :: Clustering
Classifier: Topic :: System :: Distributed Computing
Classifier: Topic :: System :: Emulators
Classifier: Topic :: System :: Networking
Classifier: Topic :: System :: Operating System
Requires-Python: >=3.8
License-File: LICENSE
License-File: NOTICE
Requires-Dist: ansible<=12.0.0,>=6.0.0
Requires-Dist: ansible-runner<=2.4.1,>=2.0.0
Requires-Dist: minimega==2.9
Requires-Dist: ClusterShell<=1.9.3
Requires-Dist: colorama<=0.4.6
Requires-Dist: coverage<=7.8.2
Requires-Dist: grpcio<=1.68.1,>=1.63.0
Requires-Dist: grpcio-tools<=1.69.0,>=1.63.0
Requires-Dist: importlib_metadata<=8.6.1,>=7.0.0
Requires-Dist: Jinja2<=3.1.6,>=3.1.2
Requires-Dist: netaddr<=1.3.0,>=0.7.0
Requires-Dist: networkx<=3.4.2,>=2.3
Requires-Dist: protobuf<6.0.0,>=5.0.0
Requires-Dist: pytest<=8.4.2
Requires-Dist: pytest-cov<=6.0.0
Requires-Dist: python-dotenv<=1.1.0
Requires-Dist: PyYAML<=6.0.2
Requires-Dist: qemu.qmp==0.0.3
Requires-Dist: requests==2.32.4
Requires-Dist: rich<14.1,>=13.6.0
Provides-Extra: mcs
Requires-Dist: firewheel-repo-base; extra == "mcs"
Requires-Dist: firewheel-repo-linux; extra == "mcs"
Requires-Dist: firewheel-repo-vyos; extra == "mcs"
Provides-Extra: format
Requires-Dist: ruff==0.11.2; extra == "format"
Provides-Extra: docs
Requires-Dist: Sphinx<=8.2.3,>=7.0.0; extra == "docs"
Requires-Dist: myst-nb<=1.2.0; extra == "docs"
Requires-Dist: sphinx-rtd-theme==3.0.2; extra == "docs"
Requires-Dist: sphinxcontrib-spelling<=8.0.1,>=7.0.0; extra == "docs"
Requires-Dist: sphinx-copybutton==0.5.2; extra == "docs"
Requires-Dist: pyenchant==3.2.2; extra == "docs"
Requires-Dist: doc8==1.1.2; extra == "docs"
Requires-Dist: pip-licenses==5.0.0; extra == "docs"
Requires-Dist: sphinx-design==0.6.1; extra == "docs"
Provides-Extra: dev
Requires-Dist: firewheel[docs,format]; extra == "dev"
Requires-Dist: pre-commit; extra == "dev"
Requires-Dist: tox~=4.0; extra == "dev"
